ydb_async/__init__.py
ydb_async/compiler.py
ydb_async/dialect.py
ydb_async-0.0.2.dist-info/METADATA
ydb_async-0.0.2.dist-info/WHEEL
ydb_async-0.0.2.dist-info/entry_points.txt
ydb_async-0.0.2.dist-info/RECORD
